Workbook
Name Aporte: Perguntas!$C$8
Name Quantidade_Anos: Perguntas!$C$9
Name Rendimento_Carteira: Perguntas!$C$4
Name TX_Mensal: Perguntas!$C$10

Sheet Perguntas
B2: Configurações
B3: Salário | C3: 10000
B4: Rendimento da Carteira | C4: 0.01
B5: Sugestão de Investimento | C5: =C3*30%
B7: Perguntas a serem respondidas:
B8: Quanto investir por mês? | C8: 3000
B9: Por quantos Anos? | C9: 5
B10: Taxa de Rendimento Mensal? | C10: 0.01079
B11: Patrimônio Acumulado? | C11: =FV(TX_Mensal,Quantidade_Anos*12,Aporte*-1)
B12: Dividendos Mensais? | C12: =C11*Rendimento_Carteira
B14: Cenários: | C14: Patrimônio | D14: Dividendo
B15: Quanto em 2 anos? | C15: =FV(TX_Mensal,2*12,Aporte*-1) | D15: =C15*Rendimento_Carteira
B16: Quanto em 5 anos? | C16: =FV(TX_Mensal,5*12,Aporte*-1) | D16: =C16*Rendimento_Carteira
B17: Quanto em 10 anos? | C17: =FV(TX_Mensal,10*12,Aporte*-1) | D17: =C17*Rendimento_Carteira
B18: Quanto em 20 anos? | C18: =FV(TX_Mensal,20*12,Aporte*-1) | D18: =C18*Rendimento_Carteira
B19: Quanto em 30 anos? | C19: =FV(TX_Mensal,30*12,Aporte*-1) | D19: =C19*Rendimento_Carteira
B21: Perfil | C21: Conservador
B22: Valor a ser investido/mês | C22: =Aporte
B24: Tipo de FII | C24: Percentual Sugerido | D24: Valores
B25: Papel | C25: =VLOOKUP($C$21&"-"&B25,Suporte!$A$3:$D$20,4,FALSE) | D25: =$C$22*C25
B26: Tijolo | C26: =VLOOKUP($C$21&"-"&B26,Suporte!$A$3:$D$20,4,FALSE) | D26: =$C$22*C26
B27: Híbrido | C27: =VLOOKUP($C$21&"-"&B27,Suporte!$A$3:$D$20,4,FALSE) | D27: =$C$22*C27
B28: FOFs | C28: =VLOOKUP($C$21&"-"&B28,Suporte!$A$3:$D$20,4,FALSE) | D28: =$C$22*C28
B29: Desenvolvimento | C29: =VLOOKUP($C$21&"-"&B29,Suporte!$A$3:$D$20,4,FALSE) | D29: =$C$22*C29
B30: Hotelaria | C30: =VLOOKUP($C$21&"-"&B30,Suporte!$A$3:$D$20,4,FALSE) | D30: =$C$22*C30
C31: =SUM(C25:C30) | D31: =SUM(D25:D30)

Sheet Suporte
A2: Chave | B2: Perfil | C2: Tipo de FII | D2: Percentual
A3: =B3&"-"&C3 | B3: Conservador | C3: Papel | D3: 0.3
A4: =B4&"-"&C4 | B4: Conservador | C4: Tijolo | D4: 0.5
A5: =B5&"-"&C5 | B5: Conservador | C5: Híbrido | D5: 0.1
A6: =B6&"-"&C6 | B6: Conservador | C6: FOFs | D6: 0.1
A7: =B7&"-"&C7 | B7: Conservador | C7: Desenvolvimento | D7: 0
A8: =B8&"-"&C8 | B8: Conservador | C8: Hotelaria | D8: 0
A9: =B9&"-"&C9 | B9: Moderado | C9: Papel | D9: 0.32
A10: =B10&"-"&C10 | B10: Moderado | C10: Tijolo | D10: 0.3
A11: =B11&"-"&C11 | B11: Moderado | C11: Híbrido | D11: 0.08
A12: =B12&"-"&C12 | B12: Moderado | C12: FOFs | D12: 0.1
A13: =B13&"-"&C13 | B13: Moderado | C13: Desenvolvimento | D13: 0.1
A14: =B14&"-"&C14 | B14: Moderado | C14: Hotelaria | D14: 0.1
... A20: =B20&"-"&C20 | B20: Agressivo | C20: Hotelaria | D20: 0.1
